{
  "title": "Legal Process Consultant",
  "type": "Part-time",
  "location": "Remote · India",
  "commitment": "Part-time · 2 to 3 days a week",
  "summary": "Codify how the next case type actually moves through court, from constituent elements to stage rules, so DRISTI can be configured for it.",
  "tags": ["Legal", "Process design"],
  "apply_url": "mailto:collaborate@pucar.org?subject=Role%20-%20Legal%20Process%20Consultant",
  "status": "Open",
  "posted": "2026-07-06",
  "published": true,
  "body": "## The role\n\nPUCAR transforms one case type at a time. Cheque dishonour is proven; the next dispute type needs its journey mapped, its rules made explicit, and its edge cases documented before a single line of configuration is written.\n\n[draft description, refine before publishing]\n\n## What you'll do\n\n- Map the end-to-end journey of the next case type, stage by stage\n- Write the rulebook: constituent elements, timelines, notice formats, escalations\n- Work with judges and registry staff to validate it against courtroom reality\n\n## Who this suits\n\n- Practising or former lawyers with strong procedural knowledge\n- Clear, precise writing\n- 2 to 3 days a week, flexibly scheduled\n\n## How it works\n\nPaid part-time engagement through a PUCAR collective member organisation, initially for six months."
}
